setup.cfg
setup.py
bin/pivportal
lib/pivportal/__init__.py
lib/pivportal/cli.py
lib/pivportal/rest.py
lib/pivportal/security.py
lib/pivportal.egg-info/PKG-INFO
lib/pivportal.egg-info/SOURCES.txt
lib/pivportal.egg-info/dependency_links.txt
lib/pivportal.egg-info/requires.txt
lib/pivportal.egg-info/top_level.txt
lib/pivportal/data_files/pivportal/index.html
lib/pivportal/data_files/pivportal/css/main.css
lib/pivportal/data_files/pivportal/css/toaster.min.css
lib/pivportal/data_files/pivportal/imgs/pivportal.ico
lib/pivportal/data_files/pivportal/js/angular-route.js
lib/pivportal/data_files/pivportal/js/angular.js
lib/pivportal/data_files/pivportal/js/app.js
lib/pivportal/data_files/pivportal/js/controllers.js
lib/pivportal/data_files/pivportal/js/satellizer.min.js
lib/pivportal/data_files/pivportal/js/toaster.min.js
lib/pivportal/data_files/pivportal/templates/dash.html
lib/pivportal/data_files/pivportal/templates/login.html
test/test_pivportal.py